gevent_ws/__init__.py
gevent_ws-2.1.0.dist-info/LICENSE
gevent_ws-2.1.0.dist-info/METADATA
gevent_ws-2.1.0.dist-info/WHEEL
gevent_ws-2.1.0.dist-info/top_level.txt
gevent_ws-2.1.0.dist-info/RECORD
