Metadata-Version: 2.1
Name: gevent-ws
Version: 2.1.0
Summary: Websocket server for gevent.pywsgi
Home-page: https://github.com/imachug/gevent-ws
Author: Ivanq
License: MIT
Platform: UNKNOWN
Requires-Python: >=3
